SwiftLogisticReg/__init__.py
SwiftLogisticReg/logistic_cpu.py
SwiftLogisticReg/logistic_gpu.py
SwiftLogisticReg-0.0.1.dist-info/LICENSE
SwiftLogisticReg-0.0.1.dist-info/METADATA
SwiftLogisticReg-0.0.1.dist-info/WHEEL
SwiftLogisticReg-0.0.1.dist-info/top_level.txt
SwiftLogisticReg-0.0.1.dist-info/RECORD
