Metadata-Version: 2.1
Name: SwiftLogisticReg
Version: 0.0.1
Summary: Efficient logistic regression in Python with GPU support
Home-page: https://github.com/NechbaMohammed/SwiftLogisticReg
Author: Nechba Mohammed, Mouhajir Mohamed, and Sedjari Yassine
Author-email: mohammednechba@gmail.com
License-File: LICENSE
